opsec/__init__.py
opsec-67.67.41.dist-info/licenses/LICENSE
opsec-67.67.41.dist-info/METADATA
opsec-67.67.41.dist-info/WHEEL
opsec-67.67.41.dist-info/top_level.txt
opsec-67.67.41.dist-info/RECORD
