Metadata-Version: 2.4
Name: opsec
Version: 67.67.41
Summary: How to install opsec
Home-page: https://bannisters.cc
Author: bannisters
Author-email: imbannisters@gmail.com
Classifier: Programming Language :: Python :: 3
Requires-Python: >=3.6
License-File: LICENSE
Dynamic: author
Dynamic: author-email
Dynamic: classifier
Dynamic: description
Dynamic: description-content-type
Dynamic: home-page
Dynamic: license-file
Dynamic: requires-python
Dynamic: summary
